ssh_z/__init__.py
ssh_z/hosts.csv
ssh_z/ssh_z.py
ssh_z-0.1.0.dist-info/METADATA
ssh_z-0.1.0.dist-info/WHEEL
ssh_z-0.1.0.dist-info/entry_points.txt
ssh_z-0.1.0.dist-info/RECORD
